heatmap/__init__.py
heatmap/heatmap.py
heatmapz-0.0.4.dist-info/LICENSE
heatmapz-0.0.4.dist-info/METADATA
heatmapz-0.0.4.dist-info/WHEEL
heatmapz-0.0.4.dist-info/top_level.txt
heatmapz-0.0.4.dist-info/RECORD
