Metadata-Version: 2.1
Name: heatmapz
Version: 0.0.4
Summary: Create heatmaps with shapes and size as a parameter
Home-page: https://github.com/drazenz/heatmap
Author: Drazen Zaric
Author-email: drazen.zaric@gmail.com
License: UNKNOWN
Platform: UNKNOWN
Classifier: Programming Language :: Python :: 3
Classifier: License :: OSI Approved :: BSD License
Classifier: Operating System :: OS Independent
Requires-Python: >=3.5
Requires-Dist: matplotlib (>=3.0.3)
Requires-Dist: pandas
Requires-Dist: seaborn
